gnnfairviz/RangesetCategorical.py
gnnfairviz/__init__.py
gnnfairviz/community.py
gnnfairviz/css.py
gnnfairviz/draw.py
gnnfairviz/eug.py
gnnfairviz/individual_bias.py
gnnfairviz/util.py
gnnfairviz/metrics/__init__.py
gnnfairviz/metrics/node_classification.py
gnnfairviz-0.0.1.post1.dist-info/LICENSE
gnnfairviz-0.0.1.post1.dist-info/METADATA
gnnfairviz-0.0.1.post1.dist-info/WHEEL
gnnfairviz-0.0.1.post1.dist-info/top_level.txt
gnnfairviz-0.0.1.post1.dist-info/RECORD
