Metadata-Version: 2.1
Name: gnnfairviz
Version: 0.0.1.post1
Summary: Official implementation of GNNFairViz
Author-email: Xinwu Ye <yexw0403@foxmail.com>
License: MIT License
Keywords: fairness,visual analysis,graph neural networks,Jupyter notebook
Classifier: Development Status :: 4 - Beta
Classifier: Programming Language :: Python :: 3
Requires-Python: <=3.11,>=3.8
License-File: LICENSE
Requires-Dist: numpy >=1.26.2
Requires-Dist: holoviews >=1.16.2
Requires-Dist: torch >=2.0.1
Requires-Dist: dgl >=1.1.1
Requires-Dist: pandas >=1.5.3
Requires-Dist: panel >=1.2.0
Requires-Dist: shapely
Requires-Dist: scikit-learn >=1.3.0
Requires-Dist: umap-learn >=0.5.5
Requires-Dist: scipy >=1.11.4
Requires-Dist: tqdm >=4.65.0
Requires-Dist: bokeh >=3.1.1
Requires-Dist: matplotlib >=3.7.1
